createpythonpackage/__init__.py
createpythonpackage/__main__.py
createpythonpackage/main.py
create_python_package-0.5.0.1.dist-info/LICENSE
create_python_package-0.5.0.1.dist-info/METADATA
create_python_package-0.5.0.1.dist-info/WHEEL
create_python_package-0.5.0.1.dist-info/entry_points.txt
create_python_package-0.5.0.1.dist-info/top_level.txt
create_python_package-0.5.0.1.dist-info/RECORD
