Metadata-Version: 2.1
Name: create-python-package
Version: 0.5.0.1
Summary: Create the file and folder structure for a Python package
Home-page: https://github.com/cs01/create-python-package
Author: Chad Smith
Author-email: grassfedcode@gmail.com
License: License :: OSI Approved :: MIT License
Keywords: package,setup
Platform: UNKNOWN
Classifier: Intended Audience :: Developers
Classifier: Operating System :: OS Independent
Classifier: License :: OSI Approved :: MIT License
Classifier: Programming Language :: Python
Classifier: Programming Language :: Python :: 3
Classifier: Intended Audience :: Developers
Requires-Python: >=3.6
Requires-Dist: cookiecutter
